MANIFEST.in
setup.cfg
setup.py
optimus/__init__.py
optimus/optimus.py
optimus/templates/__init__.py
optimus/templates/tornado/README.md
optimus/templates/tornado/alembic.ini
optimus/templates/tornado/setup.py
optimus/templates/tornado/tox.ini
optimus/templates/tornado/migrations/README
optimus/templates/tornado/migrations/env.py
optimus/templates/tornado/migrations/script.py.mako
optimus/templates/tornado/project_name/__init__.py
optimus/templates/tornado/project_name/dev
optimus/templates/tornado/project_name/log_settings.py
optimus/templates/tornado/project_name/main.py
optimus/templates/tornado/project_name/urls.py
optimus/templates/tornado/project_name/handlers/__init__.py
optimus/templates/tornado/project_name/handlers/hello.py
optimus/templates/tornado/project_name/models/__init__.py
optimus/templates/tornado/project_name/models/base.py
optimus/templates/tornado/project_name/settings/__init__.py
optimus/templates/tornado/project_name/settings/local.py
optimus/templates/tornado/project_name/settings/production.py
optimus/templates/tornado/project_name/settings/test.py
optimus/templates/tornado/project_name/static/.gitkeep
optimus/templates/tornado/project_name/templates/.gitkeep
optimus/templates/tornado/project_name/utils/__init__.py
optimus/templates/tornado/requirements/default.txt
optimus/templates/tornado/requirements/development.txt
optimus/templates/tornado/requirements/test.txt
optimus/templates/tornado/tests/__init__.py
optimus/templates/tornado/tests/__main__.py
optimus/templates/tornado/tests/base.py
optimus/templates/tornado/tests/handlers/__init__.py
optimus/templates/tornado/tests/handlers/test_hello.py
optimus/templates/tornado/tests/utils/__init__.py
optimus/utils/__init__.py
optimus/utils/command.py
py_optimus.egg-info/PKG-INFO
py_optimus.egg-info/SOURCES.txt
py_optimus.egg-info/dependency_links.txt
py_optimus.egg-info/entry_points.txt
py_optimus.egg-info/not-zip-safe
py_optimus.egg-info/requires.txt
py_optimus.egg-info/top_level.txt