Metadata-Version: 1.0
Name: py-optimus
Version: 0.0.2
Summary: Optimus is a Python web framework project constructor.
Home-page: http://github.com/johndeng/optimus
Author: John Deng
Author-email: denghuanzhong@gmail.com
License: UNKNOWN
Platform: UNKNOWN
